{
  "page": {
    "title": "reas de Trabajo - FANTEA",
    "description": "Conoce las 谩reas de trabajo de FANTEA: educaci贸n, salud, vida adulta, inclusi贸n social y vivienda. Trabajamos en todos los 谩mbitos de la vida",
    "meta": {
      "title": "reas de Trabajo - FANTEA",
      "description": "Conoce las 谩reas de trabajo de FANTEA: educaci贸n, salud, vida adulta, inclusi贸n social y vivienda. Trabajamos en todos los 谩mbitos de la vida"
    }
  },
  "hero": {
    "title": "reas de Trabajo",
    "titleHighlight": "Trabajo",
    "description": "Trabajamos en distintos 谩mbitos para mejorar la calidad de vida de las personas autistas y sus familias. Descubre c贸mo abordamos cada 谩rea con enfoques especializados y compromiso.",
    "image": "hero-inclusive.jpg",
    "imageAlt": "Personas trabajando en diferentes 谩reas de inclusi贸n",
    "buttons": [
      {
        "text": "Ver reas",
        "url": "#areas",
        "style": "primary"
      },
      {
        "text": "Nuestro Manifiesto",
        "url": "manifiesto.html",
        "style": "outline"
      }
    ]
  },
  "stats": {
    "items": [
      {
        "number": "5",
        "text": "reas de Intervenci贸n"
      },
      {
        "number": "15+",
        "text": "A帽os de Experiencia"
      },
      {
        "number": "1000+",
        "text": "Familias Atendidas"
      },
      {
        "number": "50+",
        "text": "Profesionales Formados"
      }
    ]
  },
  "areas": {
    "title": "Nuestras reas de Intervenci贸n",
    "subtitle": "En FANTEA trabajamos en distintos 谩mbitos para mejorar la calidad de vida de las personas autistas y sus familias:",
    "areas": [
      {
        "icon": "fas fa-graduation-cap",
        "title": "Educaci贸n",
        "emoji": "",
        "description": "Garantizamos una educaci贸n inclusiva y de calidad para todas las personas autistas.",
        "services": [
          "Apoyos en el aula para garantizar la inclusi贸n",
          "Modelos sostenibles como el asistente personal",
          "Formaci贸n a docentes y equipos educativos"
        ]
      },
      {
        "icon": "fas fa-heartbeat",
        "title": "Salud",
        "emoji": "",
        "description": "Promovemos una atenci贸n sanitaria accesible y especializada para el colectivo TEA.",
        "services": [
          "Atenci贸n temprana espec铆fica y accesible",
          "Salud mental adaptada y diagn贸sticos 谩giles",
          "Formaci贸n y sensibilizaci贸n de profesionales sanitarios"
        ]
      },
      {
        "icon": "fas fa-briefcase",
        "title": "Vida Adulta y Empleo",
        "emoji": "",
        "description": "Facilitamos la transici贸n a la vida adulta y la inserci贸n laboral de las personas autistas.",
        "services": [
          "Programas de autonom铆a personal",
          "Inserci贸n laboral y adaptaci贸n de entornos de trabajo",
          "Desarrollo de habilidades sociales y laborales"
        ]
      },
      {
        "icon": "fas fa-globe",
        "title": "Inclusi贸n Social",
        "emoji": "",
        "description": "Trabajamos por una sociedad m谩s inclusiva donde todas las personas tengan las mismas oportunidades.",
        "services": [
          "Acceso igualitario a la vida comunitaria",
          "Recursos de respiro familiar y conciliaci贸n",
          "Actividades de ocio y tiempo libre inclusivas"
        ]
      },
      {
        "icon": "fas fa-home",
        "title": "Vivienda y Recursos Residenciales",
        "emoji": "",
        "description": "Promovemos opciones de vivienda adaptadas que permitan una vida independiente y digna.",
        "services": [
          "Plazas adaptadas y apoyos para una vida independiente",
          "Modelos de vivienda tutelada y compartida",
          "Apoyos personalizados seg煤n las necesidades individuales"
        ]
      }
    ]
  },
  "impact": {
    "title": "Nuestro Impacto en Cada rea",
    "description": "En FANTEA hemos logrado resultados significativos en cada una de nuestras 谩reas de trabajo, mejorando la calidad de vida de miles de personas autistas y sus familias en Andaluc铆a.",
    "image": "hero-inclusive.jpg",
    "imageAlt": "Impacto de nuestro trabajo en la comunidad",
    "stats": [
      {
        "number": "95%",
        "label": "de familias satisfechas con nuestros servicios"
      },
      {
        "number": "80%",
        "label": "de 茅xito en inserci贸n laboral"
      },
      {
        "number": "100%",
        "label": "de centros educativos con formaci贸n especializada"
      }
    ]
  },
  "cta": {
    "title": "驴Quieres Conocer M谩s Sobre Nuestro Trabajo?",
    "description": "Descubre c贸mo trabajamos en cada 谩rea y c贸mo puedes participar en nuestras iniciativas para crear una sociedad m谩s inclusiva.",
    "buttons": [
      {
        "text": "Leer Nuestro Manifiesto",
        "url": "manifiesto.html",
        "style": "primary"
      },
      {
        "text": "Contactar",
        "url": "contacto.html",
        "style": "outline"
      }
    ]
  },
  "navigation": {
    "menu": [
      {
        "text": "Inicio",
        "url": "index.html"
      },
      {
        "text": "Qui茅nes somos",
        "url": "quienes-somos.html"
      },
      {
        "text": "Asociaciones federadas",
        "url": "asociaciones.html"
      },
      {
        "text": "reas",
        "url": "areas.html",
        "active": true
      },
      {
        "text": "Nuestro manifiesto",
        "url": "manifiesto.html"
      },
      {
        "text": "Prensa",
        "url": "prensa.html"
      },
      {
        "text": "Af铆liate",
        "url": "afiliate.html"
      },
      {
        "text": "Contacto",
        "url": "contacto.html"
      }
    ],
    "ctaButton": {
      "text": "nete a Nosotros",
      "url": "afiliate.html"
    }
  },
  "accessibility": {
    "skipLink": "Saltar al contenido principal",
    "buttons": {
      "increaseFont": "Aumentar texto",
      "decreaseFont": "Reducir texto",
      "highContrast": "Alto contraste",
      "dyslexiaFont": "Fuente dislexia"
    }
  }
}

