{
  "asociaciones-header": {
    "title": "Asociaciones Federadass",
    "description": "Unidos por los derechos del colectivo TEA en Andaluc铆a. Descubre las asociaciones que forman parte de FANTEA y trabajan de forma coordinada por una sociedad m谩s inclusivaa.",
    "image": "http://localhost:3001/uploads/images/asociaciones-image_1755513241964_Logo.png",
    "buttons": {
      "ver": "Ver Asociaciones",
      "verUrl": "#associations",
      "unirse": "Unirse a FANTEA",
      "unirseUrl": "#join",
      "estatutos": "Descarga Nuestros Estatutos",
      "estatutosUrl": "#download-statutes"
    },
    "lastModified": "2025-08-18T10:34:10.042Z",
    "modifiedBy": "admin"
  },
  "asociaciones-stats": {
    "stats": [
      {
        "number": "1 de 100",
        "description": "ni帽os tienen autismo"
      },
      {
        "number": "500+",
        "description": "familias andaluzas apoyadas"
      },
      {
        "number": "15",
        "description": "a帽os de experiencia"
      },
      {
        "number": "35+",
        "description": "asociaciones afiliadas"
      },
      {
        "number": "15+",
        "description": "a帽os de experiencia"
      },
      {
        "number": "35+",
        "description": "asociaciones federadas"
      },
      {
        "number": "500+",
        "description": "familias apoyadas"
      },
      {
        "number": "8",
        "description": "provincias andaluzas"
      },
      {
        "number": "35+++",
        "description": "Asociaciones Federadasss"
      },
      {
        "number": "8",
        "description": "Provincias Andaluzas"
      },
      {
        "number": "15",
        "description": "A帽os de Experiencia"
      },
      {
        "number": "5000+",
        "description": "Familias Atendidas"
      }
    ],
    "lastModified": "2025-08-18T10:34:19.966Z",
    "modifiedBy": "admin"
  },
  "asociaciones-list": {
    "sectionTitle": "Nuestras Asociacionesss",
    "subtitle": "Actualmente, forman parte de FANTEA las siguientes asociaciones que comparten nuestros valores y objetivossss:",
    "introText": "FANTEAaaa est谩 abierta a que se sumen otras asociaciones andaluzas que compartan nuestros valores y objetivos, con el fin de fortalecer la voz del colectivo y trabajar de forma coordinada.",
    "associations": [
      {
        "name": "Asociaci贸n Autismo El Puertoooo",
        "province": "C谩diz",
        "description": "Asociaci贸n dedicada al apoyo y defensa de los derechos de las personas autistas y sus familias en la provincia de C谩dizzzz.",
        "website": "info@autismoelpuerto.org"
      },
      {
        "name": "Asociaci贸n Autismo Mijas-Fuengirola",
        "province": "M谩laga",
        "description": "Asociaci贸n comprometida con la inclusi贸n y el apoyo a las personas autistas y sus familias en la Costa del Sol.",
        "website": "info@autismomijasfuengirola.org"
      },
      {
        "name": "Asociaci贸n Autismo Granada",
        "province": "Granada",
        "description": "Asociaci贸n que trabaja por la inclusi贸n y el apoyo integral a las personas autistas y sus familias en la provincia de Granada.",
        "website": "info@autismogranada.org"
      },
      {
        "name": "Asociaci贸n Autismo Sevilla",
        "province": "Sevilla",
        "description": "Asociaci贸n comprometida con la defensa de los derechos y la mejora de la calidad de vida de las personas autistas en Sevilla.",
        "website": "info@autismosevilla.org"
      },
      {
        "name": "test",
        "province": "test",
        "description": "test",
        "website": "test"
      }
    ],
    "lastModified": "2025-08-18T10:35:27.902Z",
    "modifiedBy": "admin"
  },
  "asociaciones-join": {
    "title": "驴Quieres Unirte a FANTEAa?",
    "description": "FANTEAa est谩 abierta a que se sumen otras asociaciones andaluzas que compartan nuestros valores y objetivos, con el fin de fortalecer la voz del colectivo y trabajar de forma coordinada.",
    "buttons": {
      "primary": "Solicitar Afiliaci贸nn",
      "primaryUrl": "afiliate.html",
      "secondary": "Contactarr",
      "secondaryUrl": "contacto.html"
    },
    "lastModified": "2025-08-18T10:50:02.977Z",
    "modifiedBy": "admin"
  },
  "asociaciones-benefits": {
    "benefits": [
      {
        "icon": "fas fa-bullhorn",
        "title": "Voz Unidaa",
        "description": "Mayor capacidad de incidencia pol铆tica y sociall"
      },
      {
        "icon": "fas fa-hands-helping",
        "title": "Apoyo Mutuo",
        "description": "Compartir recursos, experiencias y mejores pr谩cticas"
      },
      {
        "icon": "fas fa-users",
        "title": "Red de Contactos",
        "description": "Conectarse con otras asociaciones y profesionales"
      },
      {
        "icon": "fas fa-graduation-cap",
        "title": "Formaci贸n",
        "description": "Acceso a programas de formaci贸n y capacitaci贸n"
      }
    ],
    "lastModified": "2025-08-18T10:50:18.132Z",
    "modifiedBy": "admin"
  },
  "asociaciones-cta": {
    "title": "驴Listo para Unirte a Nuestra Redd?",
    "description": "Forma parte de la mayor red de asociaciones TEA de Andaluc铆a y trabaja junto a nosotros por una sociedad m谩s inclusiva y justaa.",
    "buttons": {
      "primary": "Solicitar Afiliaci贸nn",
      "primaryUrl": "afiliate.html",
      "secondary": "M谩s Informaci贸n",
      "secondaryUrl": "contacto.html"
    },
    "lastModified": "2025-08-18T10:50:32.420Z",
    "modifiedBy": "admin"
  },
  "asociaciones-statutes": {
    "title": "Nuestros Estatutoss",
    "description": "Descarga los estatutos oficiales de FANTEA para conocer en detalle nuestra estructura organizativa, objetivos y funcionamiento interno. Este documento es fundamental para entender c贸mo trabajamos y c贸mo puedes formar parte de nuestra federaci贸n.",
    "features": [
      "Formato PDF accesible",
      "Descarga gratuitaa",
      "Actualizado 2024"
    ],
    "lastModified": "2025-08-18T10:50:41.757Z",
    "modifiedBy": "admin"
  },
  "areas-header": {
    "title": "reas de Trabajo",
    "description": "Trabajamos en distintos 谩mbitos para mejorar la calidad de vida de las personas autistas y sus familias. Descubre c贸mo abordamos cada 谩rea con enfoques especializados y compromisoo.",
    "image": "http://localhost:3001/uploads/images/areas-header-image_1755517584816_Logo.png",
    "buttons": [
      {
        "text": "Ver reass",
        "url": "#areas"
      },
      {
        "text": "Nuestro Manifiestoo",
        "url": "/manifiesto.html"
      }
    ],
    "lastModified": "2025-08-19T09:26:14.252Z",
    "modifiedBy": "admin"
  },
  "areas-stats": {
    "items": [
      {
        "number": "55",
        "description": "reas de Intervenci贸n"
      },
      {
        "number": "15+",
        "description": "A帽os de Experiencia"
      },
      {
        "number": "1000+",
        "description": "Familias Atendidas"
      },
      {
        "number": "50+",
        "description": "Profesionales Formados"
      }
    ],
    "lastModified": "2025-08-18T11:47:02.562Z",
    "modifiedBy": "admin"
  },
  "areas-list": {
    "title": "Nuestras reas de Intervenci贸n",
    "subtitle": "En FANTEA trabajamos en distintos 谩mbitos para mejorar la calidad de vida de las personas autistas y sus familias:",
    "areas": [
      {
        "title": "Educaci贸n",
        "emoji": "",
        "description": "Garantizamos una educaci贸n inclusiva y de calidad para todas las personas autistas.",
        "features": [
          "Apoyos en el aula para garantizar la inclusi贸n",
          "Modelos sostenibles como el asistente personal",
          "Formaci贸n a docentes y equipos educativos"
        ]
      },
      {
        "title": "Salud",
        "emoji": "",
        "description": "Promovemos una atenci贸n sanitaria accesible y especializada para el colectivo TEA.",
        "features": [
          "Atenci贸n temprana espec铆fica y accesible",
          "Salud mental adaptada y diagn贸sticos 谩giles",
          "Formaci贸n y sensibilizaci贸n de profesionales sanitarios"
        ]
      },
      {
        "title": "Vida Adulta y Empleo",
        "emoji": "",
        "description": "Facilitamos la transici贸n a la vida adulta y la inserci贸n laboral de las personas autistas.",
        "features": [
          "Programas de autonom铆a personal",
          "Inserci贸n laboral y adaptaci贸n de entornos de trabajo",
          "Desarrollo de habilidades sociales y laborales"
        ]
      },
      {
        "title": "Inclusi贸n Social",
        "emoji": "",
        "description": "Trabajamos por una sociedad m谩s inclusiva donde todas las personas tengan las mismas oportunidades.",
        "features": [
          "Acceso igualitario a la vida comunitaria",
          "Recursos de respiro familiar y conciliaci贸n",
          "Actividades de ocio y tiempo libre inclusivas"
        ]
      },
      {
        "title": "Vivienda y Recursos Residenciales",
        "emoji": "",
        "description": "Promovemos opciones de vivienda adaptadas que permitan una vida independiente y digna.",
        "features": [
          "Plazas adaptadas y apoyos para una vida independiente",
          "Modelos de vivienda tutelada y compartida",
          "Apoyos personalizados seg煤n las necesidades individuales"
        ]
      }
    ],
    "lastModified": "2025-08-18T11:47:55.081Z",
    "modifiedBy": "admin"
  },
  "areas-impact": {
    "title": "Nuestro Impacto en Cada reaa",
    "description": "En FANTEA hemos logrado resultados significativos en cada una de nuestras 谩reas de trabajo, mejorando la calidad de vida de miles de personas autistas y sus familias en Andaluc铆aa.",
    "image": "http://localhost:3001/uploads/images/areas-impact-image_1755517693610_WhatsApp_Image_2025-08-11_at_22.41.27_27323bd1.jpg",
    "stats": [
      {
        "percentage": "955%",
        "description": "de familias satisfechas con nuestros servicios"
      },
      {
        "percentage": "80%",
        "description": "de 茅xito en inserci贸n laboral"
      },
      {
        "percentage": "100%",
        "description": "de centros educativos con formaci贸n especializada"
      }
    ],
    "lastModified": "2025-08-18T11:48:29.929Z",
    "modifiedBy": "admin"
  },
  "areas-cta": {
    "title": "驴Quieres Conocer M谩s Sobre Nuestro Trabajoo?",
    "description": "Descubre c贸mo trabajamos en cada 谩rea y c贸mo puedes participar en nuestras iniciativas para crear una sociedad m谩s inclusivaa.",
    "buttons": [
      {
        "text": "Leer Nuestro Manifiesto",
        "url": "/manifiesto.html"
      },
      {
        "text": "Contactar",
        "url": "/contacto.html"
      }
    ],
    "lastModified": "2025-08-18T11:48:43.233Z",
    "modifiedBy": "admin"
  },
  "manifiesto-header": {
    "title": "Nuestro Manifiestoo",
    "description": "Los compromisos y valores que gu铆an nuestra lucha por los derechos del colectivo TEA. Descubre los principios que nos mueven a trabajar por una sociedad m谩s inclusiva y justaaa.",
    "image": "http://localhost:3001/uploads/images/manifiesto-header-image_1755527186431_Logo.png",
    "buttons": [
      {
        "text": "Ver Compromisoss",
        "url": "#commitments"
      }
    ],
    "lastModified": "2025-08-18T14:26:29.494Z",
    "modifiedBy": "admin"
  },
  "manifiesto-stats": {
    "items": [
      {
        "number": "544",
        "description": "Compromisos Fundamentales"
      },
      {
        "number": "4",
        "description": "Valores Principales"
      },
      {
        "number": "15",
        "description": "A帽os de Lucha"
      },
      {
        "number": "100%",
        "description": "Compromiso con las Familias"
      }
    ],
    "lastModified": "2025-08-18T14:26:33.832Z",
    "modifiedBy": "admin"
  },
  "manifiesto-commitments": {
    "title": "Nuestros Compromisosss",
    "subtitle": "FANTEAsss nace por y para las personas autistas y sus familias, con el compromiso de:",
    "commitments": [
      {
        "title": "No dejar a nadie atr谩ssss",
        "description": "Trabajamos para que todas las personas autistas y sus familias tengan acceso a los recursos y apoyos que necesitan, sin excepci贸n.ssss",
        "icon": "fas fa-users"
      },
      {
        "title": "Defender apoyos reales, justos y gratuitos",
        "description": "Luchamos por servicios de calidad que sean accesibles para todas las familias, independientemente de su situaci贸n econ贸mica.",
        "icon": "fas fa-balance-scale"
      },
      {
        "title": "Reivindicar m谩s recursos p煤blicos",
        "description": "Exigimos m谩s recursos p煤blicos docentes, t茅cnicos y sanitarios para garantizar una atenci贸n integral y de calidad.",
        "icon": "fas fa-hand-holding-heart"
      },
      {
        "title": "Trabajar con transparencia y participaci贸n",
        "description": "Actuamos con total transparencia y fomentamos la participaci贸n activa de las familias en todas nuestras decisiones.",
        "icon": "fas fa-eye"
      },
      {
        "title": "Promover la uni贸n y colaboraci贸n",
        "description": "Fomentamos la uni贸n y la colaboraci贸n entre asociaciones para fortalecer la voz del colectivo TEA en Andaluc铆a.",
        "icon": "fas fa-hands-helping"
      }
    ],
    "lastModified": "2025-08-18T14:26:44.376Z",
    "modifiedBy": "admin"
  },
  "manifiesto-values": {
    "title": "Nuestros Valores Fundamentalesssss",
    "subtitle": "Los principios que gu铆an cada una de nuestras acciones y decisionessss",
    "values": [
      {
        "title": "Dignidadsss",
        "description": "Reconocemos la dignidad inherente de todas las personas autistas y sus familias, respetando su autonom铆a y derechos fundamentales.sss",
        "icon": "fas fa-crown"
      },
      {
        "title": "Justicia Social",
        "description": "Luchamos por la igualdad de oportunidades y el acceso a derechos fundamentales para todas las personas del colectivo TEA.",
        "icon": "fas fa-gavel"
      },
      {
        "title": "Inclusi贸n",
        "description": "Promovemos una sociedad inclusiva que valore la neurodiversidad y reconozca las capacidades de todas las personas.",
        "icon": "fas fa-heart"
      },
      {
        "title": "Empoderamiento",
        "description": "Fomentamos la autonom铆a y la participaci贸n activa de las familias en la toma de decisiones que les afectan.",
        "icon": "fas fa-rocket"
      }
    ],
    "lastModified": "2025-08-18T14:26:53.034Z",
    "modifiedBy": "admin"
  },
  "manifiesto-cta": {
    "title": "驴Compartes Nuestros Valores?ssss",
    "description": "Si tu asociaci贸n comparte estos compromisos y valores, 煤nete a FANTEA y sumemos fuerzas para defender los derechos del colectivo TEA en Andaluc铆a.sss",
    "buttons": [
      {
        "text": "Unirse a FANTEA",
        "url": "/afiliate.html"
      },
      {
        "text": "Contactar",
        "url": "/contacto.html"
      }
    ],
    "lastModified": "2025-08-18T14:26:59.295Z",
    "modifiedBy": "admin"
  },
  "prensa-header": {
    "title": "Sala de Prensaa",
    "description": "Notas de prensa, comunicados oficiales y apariciones en medios de comunicaci贸n. Mantente informado sobre las 煤ltimas noticias y actividades de FANTEAaa.",
    "image": "http://localhost:3001/uploads/images/prensa-header-image_1755530418981_Logo.png",
    "buttons": [
      {
        "text": "Ver Noticias",
        "url": "#press-items"
      },
      {
        "text": "Recursos",
        "url": "#resources"
      }
    ],
    "lastModified": "2025-08-18T15:20:28.085Z",
    "modifiedBy": "admin"
  },
  "prensa-stats": {
    "items": [
      {
        "number": "50+++",
        "description": "Notas de Prensa"
      },
      {
        "number": "25+",
        "description": "Apariciones en Medios"
      },
      {
        "number": "15+",
        "description": "Comunicados Oficiales"
      },
      {
        "number": "100+",
        "description": "Periodistas Contactados"
      }
    ],
    "lastModified": "2025-08-18T15:20:35.346Z",
    "modifiedBy": "admin"
  },
  "prensa-items": {
    "articles": [
      {
        "image": "http://localhost:3001/uploads/images/prensa-items-article1-image_1755530450165_Logo.png",
        "category": "Nota de Prensa",
        "date": "15 de Marzo, 2024",
        "type": "Nota de Prensa",
        "typeIcon": "file-alt",
        "title": "FANTEA presenta su manifiesto por los derechos del colectivo TEA",
        "description": "La Federaci贸n Andaluza TEA presenta su manifiesto con los compromisos fundamentales para defender los derechos de las personas autistas y sus familias en Andaluc铆a.",
        "linkText": "Leer m谩s",
        "linkUrl": "https://www.google.es"
      },
      {
        "image": "http://localhost:3001/images/news-2.jpg",
        "category": "Aparici贸n en Medios",
        "date": "12 de Marzo, 2024",
        "type": "Aparici贸n en Medios",
        "typeIcon": "tv",
        "title": "FANTEA en Canal Sur: La importancia de la inclusi贸n educativa",
        "description": "Nuestro presidente particip贸 en el programa \\\"Andaluc铆a Directo\\\" para hablar sobre la importancia de la inclusi贸n educativa para las personas autistas.",
        "linkText": "Ver entrevista",
        "linkUrl": "#"
      },
      {
        "image": "http://localhost:3001/images/news-3.jpg",
        "category": "Comunicado Oficial",
        "date": "8 de Marzo, 2024",
        "type": "Comunicado Oficial",
        "typeIcon": "bullhorn",
        "title": "Comunicado sobre la situaci贸n de la atenci贸n temprana en Andaluc铆a",
        "description": "FANTEA emite un comunicado oficial sobre la situaci贸n actual de la atenci贸n temprana en Andaluc铆a y las necesidades urgentes del colectivo TEA.",
        "linkText": "Leer comunicado",
        "linkUrl": "#"
      },
      {
        "image": "http://localhost:3001/images/news-1.jpg",
        "category": "Nota de Prensa",
        "date": "5 de Marzo, 2024",
        "type": "Nota de Prensa",
        "typeIcon": "file-alt",
        "title": "Nueva asociaci贸n se une a FANTEA",
        "description": "La Asociaci贸n Autismo Mijas-Fuengirola se une oficialmente a FANTEA, fortaleciendo la red de apoyo para las personas autistas en la Costa del Sol.",
        "linkText": "Leer m谩s",
        "linkUrl": "#"
      },
      {
        "image": "http://localhost:3001/images/news-2.jpg",
        "category": "Aparici贸n en Medios",
        "date": "1 de Marzo, 2024",
        "type": "Aparici贸n en Medios",
        "typeIcon": "tv",
        "title": "Entrevista en Diario Sur sobre empleo inclusivo",
        "description": "FANTEA participa en un reportaje sobre empleo inclusivo para personas autistas en la provincia de M谩laga.",
        "linkText": "Leer art铆culo",
        "linkUrl": "#"
      },
      {
        "image": "http://localhost:3001/images/news-3.jpg",
        "category": "Comunicado Oficial",
        "date": "25 de Febrero, 2024",
        "type": "Comunicado Oficial",
        "typeIcon": "bullhorn",
        "title": "Posicionamiento sobre la nueva ley de discapacidad",
        "description": "FANTEA emite su posicionamiento sobre la nueva ley de discapacidad y sus implicaciones para el colectivo TEA.",
        "linkText": "Leer posicionamiento",
        "linkUrl": "#"
      }
    ],
    "lastModified": "2025-08-18T15:22:27.808Z",
    "modifiedBy": "admin"
  },
  "prensa-content": {
    "lastModified": "2025-08-18T16:15:59.038Z",
    "modifiedBy": "admin"
  },
  "undefined": {
    "lastModified": "2025-08-20T08:52:23.445Z",
    "modifiedBy": "admin"
  },
  "afiliate-header": {
    "title": "nete a Nosotrosddd",
    "description": "Forma parte de la mayor red nacional de apoyo a las personas autistas y sus familiasddd",
    "lastModified": "2025-08-19T01:12:08.415Z",
    "modifiedBy": "admin"
  },
  "afiliate-solicitud": {
    "title": "Solicitud de Afiliaci贸n de Asociacionessfas",
    "description": "Si tu asociaci贸n comparte nuestros valores y objetivos, FANTEA es tu casa. Unirte a la federaci贸n significa sumar fuerzas para defender de forma coordinada los derechos del colectivo TEA en Andaluc铆a.sfasfsafasf",
    "lastModified": "2025-08-19T01:22:44.740Z",
    "modifiedBy": "admin"
  },
  "afiliate-beneficios": {
    "title": "Beneficios para Asociaciones Afiliadas:sfsdf",
    "items": [
      "Representaci贸n a nivel nacionalafsfdsaf",
      "Acceso a formaci贸n especializada",
      "Materiales educativos y recursos",
      "Apoyo t茅cnico y asesoramiento",
      "Participaci贸n en proyectos nacionales",
      "Red de contactos y colaboraci贸n",
      "Certificaci贸n de calidad"
    ],
    "lastModified": "2025-08-19T01:23:01.665Z",
    "modifiedBy": "admin"
  },
  "afiliate-requisitos": {
    "title": "Requisitos:asfsaf",
    "items": [
      "Ser una organizaci贸n sin 谩nimo de lucroasfsf",
      "Tener objetivos alineados con nuestra misi贸nasfdsf",
      "Contar con al menos 2 a帽os de actividad",
      "Presentar documentaci贸n legal actualizada",
      "Compromiso con los valores de la federaci贸n"
    ],
    "lastModified": "2025-08-19T01:23:12.155Z",
    "modifiedBy": "admin"
  },
  "afiliate-formulario": {
    "title": "Formulario de Solicitud de Afiliaci贸nsafasfsaf",
    "description": "Utiliza el formulario oficial de FANTEA para solicitar la afiliaci贸n de tu asociaci贸n:sfas",
    "note": "Nota: Este formulario es el canal oficial para solicitar la afiliaci贸n de asociaciones a FANTEA. Una vez enviado, nuestro equipo se pondr谩 en contacto contigo para continuar con el proceso.",
    "lastModified": "2025-08-19T01:23:20.026Z",
    "modifiedBy": "admin"
  },
  "afiliate-impacto": {
    "title": "Tu Participaci贸n Marca la Diferenciasfsaf",
    "description": "Conoce el impacto real de formar parte de nuestra comunidadsfasf",
    "stats": {
      "personasBeneficiadas": "15,000sf",
      "personasBeneficiadasText": "Personas beneficiadas",
      "asociacionesAfiliadas": "52",
      "asociacionesAfiliadasText": "Asociaciones afiliadas",
      "voluntariosActivos": "300+",
      "voluntariosActivosText": "Voluntarios activos",
      "familiasColaboradoras": "1,200+",
      "familiasColaboradorasText": "Familias colaboradoras"
    },
    "lastModified": "2025-08-19T01:23:29.058Z",
    "modifiedBy": "admin"
  },
  "afiliate-testimonios": {
    "testimonios": [
      {
        "texto": "Formar parte de esta federaci贸n ha sido fundamental para elsfasasfsafsf desarrollo de nuestra asociaci贸n local. El apoyo y los recursos compartidos nos han permitido ayudar a muchas m谩s familias.",
        "nombre": "Ana Garc铆a",
        "cargo": "Presidenta, Asociaci贸n Autismo Sevilla",
        "imagen": "images/testimonial-1.jpg"
      },
      {
        "texto": "Como familia afiliada, hemos encontrado el apoyo y la orientaci贸n que necesit谩bamos. La red de contactos y los recursos disponibles han sido invaluables para el desarrollo de nuestro hijo.",
        "nombre": "Carlos y Mar铆a Mendoza",
        "cargo": "Familia Afiliada, Madrid",
        "imagen": "images/testimonial-2.jpg"
      },
      {
        "texto": "Ser voluntario aqu铆 me ha dado la oportunidad de contribuir de manera significativa a una causa que considero fundamental. Cada evento y cada familia a la que ayudo me llena de satisfacci贸n.",
        "nombre": "Luis Rodr铆guez",
        "cargo": "Voluntario desde 2019",
        "imagen": "images/testimonial-3.jpg"
      }
    ],
    "lastModified": "2025-08-19T01:23:36.618Z",
    "modifiedBy": "admin"
  },
  "afiliate-donaciones": {
    "title": "Donaciones y Patrociniosasfsdf",
    "description": "Tu aportaci贸n econ贸mica nos ayuda a mantener y ampliar nuestros programas en Andaluc铆aafsafas",
    "lastModified": "2025-08-19T01:23:49.089Z",
    "modifiedBy": "admin"
  },
  "contacto-header": {
    "title": "holaaaaaaa",
    "description": "Estamos aqu铆 para ayudarte. Contacta con nodfgdgfdgsotros paraasdasasd cualquier consulta, informaci贸n o apoyo que necesites",
    "lastModified": "2025-08-19T09:49:55.806Z",
    "modifiedBy": "admin"
  },
  "contacto-info": {
    "formTitle": "sfasda",
    "formSubtitle": "Completa el formulario y nos sadasdadaspondremos en contacto contigo lo antes podfgdfgdfible",
    "contactInfo": {
      "direcci贸n": "Calle Principal 123, 41001 Sevilla, Espa帽a",
      "tel茅fonoprincipal": "+34 954 123 456dgdfg",
      "tel茅fonosecundario": "+34 600 123 456",
      "emailprincipal": "info@fantea.org",
      "emaildeprensa": "prensa@fantea.org",
      "horariodeatenci贸n": "Lunes a Viernes: 9:00 - 17:00"
    },
    "socialLinks": {
      "facebook": "https://facebook.com/fantea",
      "twitter/x": "https://twitter.com/fantea",
      "instagram": "https://instagram.com/fantea",
      "linkedin": "https://linkedin.com/company/fantea",
      "youtube": "https://youtube.com/fantea"
    },
    "lastModified": "2025-08-19T09:26:47.511Z",
    "modifiedBy": "admin"
  },
  "contacto-apoyo": {
    "title": "L铆nea de Apoyo 24/7dgdfgfvfg",
    "number": "900 800 700dfgdg",
    "description": "Apoyo emocional y orientaci贸n para familias en situaciones de crisisdfgdf",
    "lastModified": "2025-08-19T01:58:08.067Z",
    "modifiedBy": "admin"
  },
  "contacto-banner": {
    "title": "Contacto - TEST NUEVO",
    "description": "Descripci贸n de prueba del nuevo CMS - 11:32:37",
    "lastModified": "2025-08-19T09:32:37.714Z",
    "modifiedBy": "admin"
  },
  "statutes": {
    "filename": "print-1755597942194-662236670.pdf",
    "originalName": "print.pdf",
    "path": "D:\\Proyects\\Fantea\\data\\uploads\\estatutos\\print-1755597942194-662236670.pdf",
    "url": "/uploads/estatutos/print-1755597942194-662236670.pdf",
    "size": 219073,
    "mimetype": "application/pdf",
    "uploadedAt": "2025-08-19T10:05:42.198Z",
    "uploadedBy": "admin"
  },
  "footer-logo": {
    "title": "fantessssssa",
    "description": "Federaci贸n Andaluza de Autismo. Trabajando por la inclusi贸n y los derechos de las personas autistas en Andaluc铆a desde 2009.safsaf",
    "lastModified": "2025-08-19T12:31:42.084Z",
    "modifiedBy": "admin"
  },
  "footer-resources": {
    "title": "Recursosafasfs",
    "links": [
      {
        "text": "Estatutos",
        "url": "estatutos.html"
      },
      {
        "text": "Gu铆as para Familias",
        "url": "#"
      },
      {
        "text": "Formaci贸n Profesional",
        "url": "#"
      },
      {
        "text": "Centro de Descargas",
        "url": "#"
      },
      {
        "text": "Preguntas Frecuentes",
        "url": "#"
      },
      {
        "text": "Pol铆tica de Privacidad",
        "url": "#"
      }
    ],
    "lastModified": "2025-08-19T10:35:12.554Z",
    "modifiedBy": "admin"
  },
  "footer-social": {
    "facebook": "https://facebook.com/fantea",
    "twitter": "https://twitter.com/fantea",
    "instagram": "https://instagram.com/fanteass",
    "linkedin": "https://linkedin.com/company/fantea",
    "youtube": "https://youtube.com/fantea",
    "lastModified": "2025-08-19T11:27:58.578Z",
    "modifiedBy": "admin"
  },
  "footer-navigation": {
    "title": "Navegaci贸n",
    "links": [
      {
        "text": "Sobre Nosotros",
        "url": "quienes-somos.html"
      },
      {
        "text": "Asociaciones Federadas",
        "url": "asociaciones.html"
      },
      {
        "text": "reas",
        "url": "areas.html"
      },
      {
        "text": "Nuestro Manifiesto",
        "url": "manifiesto.html"
      },
      {
        "text": "Prensa",
        "url": "prensa.html"
      },
      {
        "text": "Af铆liate",
        "url": "afiliate.html"
      }
    ],
    "lastModified": "2025-08-19T10:54:37.320Z",
    "modifiedBy": "admin"
  },
  "footer-contact": {
    "title": "Contacto",
    "address": "Calle Principal 123, Sevilla",
    "phone": "+34 954 123 456",
    "email": "info@fantea.org",
    "buttonText": "Contactar",
    "lastModified": "2025-08-19T10:54:37.332Z",
    "modifiedBy": "admin"
  },
  "footer-bottom": {
    "copyright": "漏 2024 FANTEA - Federaci贸n Andaluza de Autismo. Todos los derechos reservados.",
    "links": [
      {
        "text": "Pol铆tica de Privacidad",
        "url": "#"
      },
      {
        "text": "T茅rminos de Uso",
        "url": "#"
      },
      {
        "text": "Cookies",
        "url": "#"
      }
    ],
    "lastModified": "2025-08-19T10:54:37.361Z",
    "modifiedBy": "admin"
  }
}